{
  "resources": [
    {
      "id": 1,
      "title": "What is Photosynthesis?",
      "category": "Science",
      "type": "Video",
      "thumbnailUrl": "https://images.unsplash.com/photo-1698892289193-eb8b082ecce3?q=80&w=1932&auto=format&fit=crop&ixlib=rb-4.1.0&ixid=M3wxMjA3fDB8MHxwaG90by1wYWdlfHx8fGVufDB8fHx8fA%3D%3D",
      "readTime": 4,
      "isLiked": false,
      "link": "https://www.youtube.com/watch?v=UPBMG5EYydo"
    },
    {
      "id": 2,
      "title": "Basic Algebra Explained",
      "category": "Math",
      "type": "Video",
      "thumbnailUrl": "https://images.unsplash.com/photo-1711552466487-ac9afb5528cb?q=80&w=2067&auto=format&fit=crop&ixlib=rb-4.1.0&ixid=M3wxMjA3fDB8MHxwaG90by1wYWdlfHx8fGVufDB8fHx8fA%3D%3D",
      "readTime": 9,
      "isLiked": false,
      "link": "https://www.youtube.com/watch?v=NybHckSEQBI"
    },
    {
      "id": 3,
      "title": "Grammar Guide: 12 Common Mistakes",
      "category": "Language",
      "type": "Article",
      "thumbnailUrl": "https://images.unsplash.com/photo-1501504905252-473c47e087f8?q=80&w=1974&auto=format&fit=crop&ixlib=rb-4.1.0&ixid=M3wxMjA3fDB8MHxwaG90by1wYWdlfHx8fGVufDB8fHx8fA%3D%3D",
      "readTime": 6,
      "isLiked": false,
      "link": "https://medium.com/@englishlessons/12-common-grammar-mistakes-295cf501d1ca"
    },
    {
      "id": 4,
      "title": "The Solar System 101",
      "category": "Science",
      "type": "Video",
      "thumbnailUrl": "https://images.unsplash.com/photo-1692342593304-9fb0b1bed6e4?q=80&w=1963&auto=format&fit=crop&ixlib=rb-4.1.0&ixid=M3wxMjA3fDB8MHxwaG90by1wYWdlfHx8fGVufDB8fHx8fA%3D%3D",
      "readTime": 7,
      "isLiked": false,
      "link": "https://www.youtube.com/watch?v=libKVRa01L8"
    },
    {
      "id": 5,
      "title": "Understanding Fractions Easily",
      "category": "Math",
      "type": "Article",
      "thumbnailUrl": "https://images.unsplash.com/photo-1741997852952-34de866f085b?q=80&w=1932&auto=format&fit=crop&ixlib=rb-4.1.0&ixid=M3wxMjA3fDB8MHxwaG90by1wYWdlfHx8fGVufDB8fHx8fA%3D%3D",
      "readTime": 5,
      "isLiked": false,
      "link": "https://www.khanacademy.org/math/arithmetic/fraction-arithmetic"
    },
    {
      "id": 6,
      "title": "Public Speaking Tips for Kids",
      "category": "Skills",
      "type": "Video",
      "thumbnailUrl": "https://images.unsplash.com/photo-1543062591-e3c0fdb97350?q=80&w=2070&auto=format&fit=crop&ixlib=rb-4.1.0&ixid=M3wxMjA3fDB8MHxwaG90by1wYWdlfHx8fGVufDB8fHx8fA%3D%3D",
      "readTime": 8,
      "isLiked": false,
      "link": "https://www.youtube.com/watch?v=fjPI9VfzAqU"
    },
    {
      "id": 7,
      "title": "The Water Cycle | National Geographic",
      "category": "Science",
      "type": "Video",
      "thumbnailUrl": "https://images.unsplash.com/photo-1444525873963-75d329ef9e1b?q=80&w=2070&auto=format&fit=crop&ixlib=rb-4.1.0&ixid=M3wxMjA3fDB8MHxwaG90by1wYWdlfHx8fGVufDB8fHx8fA%3D%3D",
      "readTime": 3,
      "isLiked": false,
      "link": "https://www.youtube.com/watch?v=IO9tT186mZw"
    },
    {
      "id": 8,
      "title": "Geometry Basics: Shapes and Angles",
      "category": "Math",
      "type": "Video",
      "thumbnailUrl": "https://images.unsplash.com/photo-1485736982040-28ae1d52881d?q=80&w=2071&auto=format&fit=crop&ixlib=rb-4.1.0&ixid=M3wxMjA3fDB8MHxwaG90by1wYWdlfHx8fGVufDB8fHx8fA%3D%3D",
      "readTime": 10,
      "isLiked": false,
      "link": "https://www.youtube.com/watch?v=xCdxURXMdFY"
    },
    {
      "id": 9,
      "title": "How to Improve Your Vocabulary",
      "category": "Language",
      "type": "Article",
      "thumbnailUrl": "https://images.unsplash.com/photo-1552321046-a54642dc0cb8?q=80&w=2155&auto=format&fit=crop&ixlib=rb-4.1.0&ixid=M3wxMjA3fDB8MHxwaG90by1wYWdlfHx8fGVufDB8fHx8fA%3D%3D",
      "readTime": 4,
      "isLiked": false,
      "link": "https://www.oxfordlearning.com/5-simple-ways-improve-childs-vocabulary/"
    },
    {
      "id": 10,
      "title": "Mindfulness for Kids",
      "category": "Skills",
      "type": "Video",
      "thumbnailUrl": "https://images.unsplash.com/photo-1682278763548-f349e3c73793?q=80&w=2067&auto=format&fit=crop&ixlib=rb-4.1.0&ixid=M3wxMjA3fDB8MHxwaG90by1wYWdlfHx8fGVufDB8fHx8fA%3D%3D",
      "readTime": 6,
      "isLiked": false,
      "link": "https://www.youtube.com/watch?v=WPni755-Krg"
    }
  ]
}
